nonebot_plugin_web_config/__init__.py
nonebot_plugin_web_config/requirements.txt
nonebot_plugin_web_config/web_config/__init__.py
nonebot_plugin_web_config/web_config/util.py
nonebot_plugin_web_config/web_ui/__init__.py
nonebot_plugin_web_config/web_ui/config.py
nonebot_plugin_web_config/web_ui/router.py
nonebot_plugin_web_config/web_ui/templates/index.jinja2
nonebot_plugin_web_config/web_ui/templates/login.html
nonebot_plugin_web_config/web_ui/templates/static/add.png
nonebot_plugin_web_config/web_ui/templates/static/delete.png
nonebot_plugin_web_config/web_ui/templates/static/edit.png
nonebot_plugin_web_config/web_ui/templates/static/nonebot_logo.png
nonebot_plugin_web_config/web_ui/templates/static/save.png
nonebot_plugin_web_config/web_ui/util.py
nonebot_plugin_web_config-0.1.3.dist-info/METADATA
nonebot_plugin_web_config-0.1.3.dist-info/WHEEL
nonebot_plugin_web_config-0.1.3.dist-info/RECORD
