Metadata-Version: 2.1
Name: nonebot-plugin-web-config
Version: 0.1.3
Summary: Nonebot的热更新webui的基于pydantic的配置
Author: canxin
Author-email: 1969730106@qq.com
Requires-Python: >=3.8,<4.0
Classifier: Programming Language :: Python :: 3
Classifier: Programming Language :: Python :: 3.8
Classifier: Programming Language :: Python :: 3.9
Classifier: Programming Language :: Python :: 3.10
Classifier: Programming Language :: Python :: 3.11
Requires-Dist: fastapi (>=0.101.0,<0.102.0)
Requires-Dist: fastapi-login (>=1.9.1,<2.0.0)
Requires-Dist: nonebot2 (>=2.0.0,<3.0.0)
Requires-Dist: python-multipart (>=0.0.6,<0.0.7)
Requires-Dist: uvicorn (>=0.23.2,<0.24.0)
